.gitignore
.svnignore
MANIFEST.in
README.txt
setup.py
slc.stickystatusmessages-configure.zcml
docs/HISTORY.txt
src/slc/__init__.py
src/slc.stickystatusmessages.egg-info/PKG-INFO
src/slc.stickystatusmessages.egg-info/SOURCES.txt
src/slc.stickystatusmessages.egg-info/dependency_links.txt
src/slc.stickystatusmessages.egg-info/entry_points.txt
src/slc.stickystatusmessages.egg-info/namespace_packages.txt
src/slc.stickystatusmessages.egg-info/not-zip-safe
src/slc.stickystatusmessages.egg-info/paster_plugins.txt
src/slc.stickystatusmessages.egg-info/requires.txt
src/slc.stickystatusmessages.egg-info/top_level.txt
src/slc/stickystatusmessages/README.txt
src/slc/stickystatusmessages/__init__.py
src/slc/stickystatusmessages/config.py
src/slc/stickystatusmessages/configure.zcml
src/slc/stickystatusmessages/events.py
src/slc/stickystatusmessages/interfaces.py
src/slc/stickystatusmessages/notification.py
src/slc/stickystatusmessages/utils.py
src/slc/stickystatusmessages/zope2.py
src/slc/stickystatusmessages/browser/__init__.py
src/slc/stickystatusmessages/browser/configure.zcml
src/slc/stickystatusmessages/browser/interfaces.py
src/slc/stickystatusmessages/browser/views.py
src/slc/stickystatusmessages/browser/javascripts/stickystatusmessages.js
src/slc/stickystatusmessages/browser/stylesheets/stickystatusmessages.css
src/slc/stickystatusmessages/browser/templates/stickystatusmessages.pt
src/slc/stickystatusmessages/browser/thirdparty/jquery.bigtarget.1.0.1.js
src/slc/stickystatusmessages/profiles/default/browserlayer.xml
src/slc/stickystatusmessages/profiles/default/controlpanel.xml
src/slc/stickystatusmessages/profiles/default/cssregistry.xml
src/slc/stickystatusmessages/profiles/default/jsregistry.xml
src/slc/stickystatusmessages/profiles/default/metadata.xml
src/slc/stickystatusmessages/profiles/default/registry.xml
src/slc/stickystatusmessages/tests/__init__.py
src/slc/stickystatusmessages/tests/base.py
src/slc/stickystatusmessages/tests/test_statusmessages.py
src/slc/stickystatusmessages/tests/test_views.py