Metadata-Version: 1.0
Name: slc.stickystatusmessages
Version: 0.4
Summary: Provides sticky status messages to members for all the folders in which they are assigned local roles
Home-page: http://plone.org/products/slc.stickystatusmessages
Author: JC Brand, Syslab.com GmbH
Author-email: brand@syslab.com
License: GPL
Keywords: statusmessage status sticky CMFNotification
Platform: UNKNOWN
Classifier: Programming Language :: Python
